eig/__init__.py
eig/baselines/Baseline.py
eig/baselines/BaselineLatent.py
eig/baselines/__init__.py
eig/feature_significance/FeatureSignificance.py
eig/feature_significance/__init__.py
eig/interpreters/DeepNetworkModel.py
eig/interpreters/Interpreter.py
eig/interpreters/LatentLinearInterpreter.py
eig/interpreters/LatentLinearInterpreterLatentBL.py
eig/interpreters/LatentModel.py
eig/interpreters/LatentNeighborsInterpreter.py
eig/interpreters/LatentNeighborsInterpreterLatentBL.py
eig/interpreters/LinearInterpreter.py
eig/interpreters/LinearInterpreterLatentBL.py
eig/interpreters/NeighborsInterpreter.py
eig/interpreters/NeighborsInterpreterLatentBL.py
eig/interpreters/__init__.py
eig/paths/PathGeneratorAbstract.py
eig/paths/PathGeneratorLatentLinear.py
eig/paths/PathGeneratorLatentNeighbors.py
eig/paths/PathGeneratorLinear.py
eig/paths/PathGeneratorNeighbors.py
eig/paths/__init__.py
eig/paths/normal_gradients.py
eig/paths/path_generator.py
eig/paths/path_integrated_gradients.py
eig/paths/path_outliers_correct.py
eig/paths/path_utils.py
eig-0.1.4.dist-info/LICENSE
eig-0.1.4.dist-info/METADATA
eig-0.1.4.dist-info/WHEEL
eig-0.1.4.dist-info/top_level.txt
eig-0.1.4.dist-info/RECORD
