Metadata-Version: 2.1
Name: eig
Version: 0.1.4
Summary: Enhanced Integrated Gradients - a method of attributing the prediction of a deep network to its input features
Home-page: https://bitbucket.org/biociphers/eig/src/master/
Author: BioCiphers
Author-email: info@biociphers.org
License: MIT License
Platform: UNKNOWN
Classifier: Programming Language :: Python :: 3
Classifier: License :: OSI Approved :: MIT License
Classifier: Operating System :: OS Independent
Requires-Dist: numpy
Requires-Dist: scikit-learn
Requires-Dist: statsmodels
Requires-Dist: tensorflow
